Wallace Tree/full_adder.v
module  full_adder(S, Cout, A, B, Cin);
    input A, B, Cin;
    output S, Cout;
    wire w1, w2, w3;
    
    xor Sresults(S, A, B, Cin);
    and A_and_B(w1, A, B);
    and A_and_Cin(w2, A, Cin);
    and B_and_Cin(w3, B, Cin);
    or Cresults(Cout, w1, w2, w3);

endmodule

array_divider/divider_cell.v
module divider_cell(Sum, Cout, Din, Bin, Cin, Ain);

    input Ain, Bin, Cin, Din;
    output Sum, Cout;
    
    wire w_add_A;
    xor add_A(w_add_A, Ain, Din);
    full_adder FA(Sum, Cout, w_add_A, Bin, Cin);

endmodule

array_divider/array_divider_4b.v
module array_divider_4b(Q, data_operandA, data_operandB); //, clock, ctrl_DIV, data_resultRDY

    input [3:0] data_operandA, data_operandB;
    input clock, ctrl_DIV;
    output [3:0] Q;
    output data_resultRDY;

    wire [6:0] dividend;
    wire [3:0] divisor;

    
    //TODO: check if needs to be unsigned
    assign divisor = data_operandB;
    assign dividend[3:0] = data_operandA; //replace with output of negating maybe
    assign dividend[6:4] = 3'b0;

    // (Sum, Cout, Din, Bin, Cin, Ain);
    
    //row 0
    wire c_0_0, c_0_1, c_0_2, c_0_3;
    wire empty0, s_0_1, s_0_2, s_0_3;

    divider_cell cell_0_0(empty0, c_0_0, divisor[3], dividend[6], c_0_1, 1'b1);
    divider_cell cell_0_1(s_0_1, c_0_1, divisor[2], dividend[5], c_0_2, 1'b1);
    divider_cell cell_0_2(s_0_2, c_0_2, divisor[1], dividend[4], c_0_3, 1'b1);
    divider_cell cell_0_3(s_0_3, c_0_3, divisor[0], dividend[3], 1'b1, 1'b1);

    assign Q[3] = c_0_0;

    //row 1
    wire c_1_1, c_1_2, c_1_3, c_1_4;
    wire empty1, s_1_2, s_1_3, s_1_4;

    divider_cell cell_1_1(empty1, c_1_1, divisor[3], s_0_1, c_1_2, c_0_0);
    divider_cell cell_1_2(s_1_2, c_1_2, divisor[2], s_0_2, c_1_3, c_0_0);
    divider_cell cell_1_3(s_1_3, c_1_3, divisor[1], s_0_3, c_1_4, c_0_0);
    divider_cell cell_1_4(s_1_4, c_1_4, divisor[0], dividend[2], c_0_0, c_0_0);

    assign Q[2] = c_1_1;

    //row 2
    wire c_2_2, c_2_3, c_2_4, c_2_5;
    wire empty2, s_2_3, s_2_4, s_2_5;

    divider_cell cell_2_2(empty2, c_2_2, divisor[3], s_1_2, c_2_3, c_1_1);
    divider_cell cell_2_3(s_2_3, c_2_3, divisor[2], s_1_3, c_2_4, c_1_1);
    divider_cell cell_2_4(s_2_4, c_2_4, divisor[1], s_1_4, c_2_5, c_1_1);
    divider_cell cell_2_5(s_2_5, c_2_5, divisor[0], dividend[1], c_1_1, c_1_1);

    assign Q[1] = c_2_2;

    //row 3 (final row)

    wire c_3_3, c_3_4, c_3_5, c_3_6;
    wire empty3, s_3_4, s_3_5, s_3_6;

    divider_cell cell_3_3(empty3, c_3_3, divisor[3], s_2_3, c_3_4, c_2_2);
    divider_cell cell_3_4(s_3_4, c_3_4, divisor[2], s_2_4, c_3_5, c_2_2);
    divider_cell cell_3_5(s_3_5, c_3_5, divisor[1], s_2_5, c_3_6, c_2_2);
    divider_cell cell_3_6(s_3_6, c_3_6, divisor[0], dividend[0], c_2_2, c_2_2);

    assign Q[0] = c_3_3;

endmodule

array_divider/array_divider_4b_tb.v
`timescale 1ns / 1ps

module array_divider_4b_tb;

reg signed [3:0] data_operandA, data_operandB; // Use signed for two's complement
wire signed [3:0] data_result; // Use signed for two's complement

// Instance of wallaceTree module
array_divider_4b uut (
    .Q(data_result), .data_operandA(data_operandA), .data_operandB(data_operandB)
); //, .clock(1'b1), .ctrl_DIV(1'b1), .data_resultRDY(1'b1)

initial begin
    // Initialize inputs in two's complement
    data_operandA = 4'sb0000;
    data_operandB = 4'sb0000;

    $dumpfile("array_divider_4b_tb.vcd");
    $dumpvars(0, array_divider_4b_tb);

    // Iterate through all possible input combinations
    repeat (8) begin
        data_operandB = 4'sd0; // Reset data_operandB for each new data_operandA value
        repeat (8) begin
            #10; // Wait 10 time units; adjust this delay as needed
            data_operandB = data_operandB + 4'sd1;
        end
        data_operandA = data_operandA + 4'sd1;
    end

    data_operandA = 4'sd0;
    data_operandB = 4'sd0;
    repeat (8) begin
        data_operandB = 4'sd0; // Reset data_operandB for each new data_operandA value
        repeat (8) begin
            #10; // Wait 10 time units; adjust this delay as needed
            data_operandB = data_operandB - 4'sd1;
        end
        data_operandA = data_operandA - 4'sd1;
    end

    data_operandA = 4'sd0;
    data_operandB = 4'sd0;
    repeat (8) begin
        data_operandB = 4'sd0; // Reset data_operandB for each new data_operandA value
        repeat (8) begin
            #10; // Wait 10 time units; adjust this delay as needed
            data_operandB = data_operandB + 4'sd1;
        end
        data_operandA = data_operandA - 4'sd1;
    end

    data_operandA = 4'sd0;
    data_operandB = 4'sd0;
    repeat (8) begin
        data_operandB = 4'sd0; // Reset data_operandB for each new data_operandA value
        repeat (8) begin
            #10; // Wait 10 time units; adjust this delay as needed
            data_operandB = data_operandB - 4'sd1;
        end
        data_operandA = data_operandA + 4'sd1;
    end
    
    #10; // Wait for the last operation to complete
    $finish; // End the simulation
end

// Optional: Display test results
initial begin
    $monitor("At time %t, data_operandA = %d, data_operandB = %d, Q = %d",
             $time, data_operandA, data_operandB, data_result);
end

endmodule

array_divider/array_divider_4b_tb.vcd
$date
	Tue Feb 13 15:34:43 2024
$end
$version
	Icarus Verilog
$end
$timescale
	1ps
$end
$scope module array_divider_4b_tb $end
$var wire 4 ! data_result [3:0] $end
$var reg 4 " data_operandA [3:0] $end
$var reg 4 # data_operandB [3:0] $end
$scope module uut $end
$var wire 1 $ clock $end
$var wire 1 % ctrl_DIV $end
$var wire 4 & data_operandA [3:0] $end
$var wire 4 ' data_operandB [3:0] $end
$var wire 1 ( data_resultRDY $end
$var wire 4 ) divisor [3:0] $end
$var wire 1 * s_3_6 $end
$var wire 1 + s_3_5 $end
$var wire 1 , s_3_4 $end
$var wire 1 - s_2_5 $end
$var wire 1 . s_2_4 $end
$var wire 1 / s_2_3 $end
$var wire 1 0 s_1_4 $end
$var wire 1 1 s_1_3 $end
$var wire 1 2 s_1_2 $end
$var wire 1 3 s_0_3 $end
$var wire 1 4 s_0_2 $end
$var wire 1 5 s_0_1 $end
$var wire 1 6 empty3 $end
$var wire 1 7 empty2 $end
$var wire 1 8 empty1 $end
$var wire 1 9 empty0 $end
$var wire 7 : dividend [6:0] $end
$var wire 1 ; c_3_6 $end
$var wire 1 < c_3_5 $end
$var wire 1 = c_3_4 $end
$var wire 1 > c_3_3 $end
$var wire 1 ? c_2_5 $end
$var wire 1 @ c_2_4 $end
$var wire 1 A c_2_3 $end
$var wire 1 B c_2_2 $end
$var wire 1 C c_1_4 $end
$var wire 1 D c_1_3 $end
$var wire 1 E c_1_2 $end
$var wire 1 F c_1_1 $end
$var wire 1 G c_0_3 $end
$var wire 1 H c_0_2 $end
$var wire 1 I c_0_1 $end
$var wire 1 J c_0_0 $end
$var wire 4 K Q [3:0] $end
$scope module cell_0_0 $end
$var wire 1 L Ain $end
$var wire 1 M Bin $end
$var wire 1 N Din $end
$var wire 1 O w_add_A $end
$var wire 1 9 Sum $end
$var wire 1 J Cout $end
$var wire 1 I Cin $end
$scope module FA $end
$var wire 1 O A $end
$var wire 1 M B $end
$var wire 1 J Cout $end
$var wire 1 9 S $end
$var wire 1 P w1 $end
$var wire 1 Q w2 $end
$var wire 1 R w3 $end
$var wire 1 I Cin $end
$upscope $end
$upscope $end
$scope module cell_0_1 $end
$var wire 1 S Ain $end
$var wire 1 T Bin $end
$var wire 1 U Din $end
$var wire 1 V w_add_A $end
$var wire 1 5 Sum $end
$var wire 1 I Cout $end
$var wire 1 H Cin $end
$scope module FA $end
$var wire 1 V A $end
$var wire 1 T B $end
$var wire 1 I Cout $end
$var wire 1 5 S $end
$var wire 1 W w1 $end
$var wire 1 X w2 $end
$var wire 1 Y w3 $end
$var wire 1 H Cin $end
$upscope $end
$upscope $end
$scope module cell_0_2 $end
$var wire 1 Z Ain $end
$var wire 1 [ Bin $end
$var wire 1 \ Din $end
$var wire 1 ] w_add_A $end
$var wire 1 4 Sum $end
$var wire 1 H Cout $end
$var wire 1 G Cin $end
$scope module FA $end
$var wire 1 ] A $end
$var wire 1 [ B $end
$var wire 1 H Cout $end
$var wire 1 4 S $end
$var wire 1 ^ w1 $end
$var wire 1 _ w2 $end
$var wire 1 ` w3 $end
$var wire 1 G Cin $end
$upscope $end
$upscope $end
$scope module cell_0_3 $end
$var wire 1 a Ain $end
$var wire 1 b Bin $end
$var wire 1 c Cin $end
$var wire 1 d Din $end
$var wire 1 e w_add_A $end
$var wire 1 3 Sum $end
$var wire 1 G Cout $end
$scope module FA $end
$var wire 1 e A $end
$var wire 1 b B $end
$var wire 1 c Cin $end
$var wire 1 G Cout $end
$var wire 1 3 S $end
$var wire 1 f w1 $end
$var wire 1 g w2 $end
$var wire 1 h w3 $end
$upscope $end
$upscope $end
$scope module cell_1_1 $end
$var wire 1 J Ain $end
$var wire 1 5 Bin $end
$var wire 1 i Din $end
$var wire 1 j w_add_A $end
$var wire 1 8 Sum $end
$var wire 1 F Cout $end
$var wire 1 E Cin $end
$scope module FA $end
$var wire 1 j A $end
$var wire 1 5 B $end
$var wire 1 F Cout $end
$var wire 1 8 S $end
$var wire 1 k w1 $end
$var wire 1 l w2 $end
$var wire 1 m w3 $end
$var wire 1 E Cin $end
$upscope $end
$upscope $end
$scope module cell_1_2 $end
$var wire 1 J Ain $end
$var wire 1 4 Bin $end
$var wire 1 n Din $end
$var wire 1 o w_add_A $end
$var wire 1 2 Sum $end
$var wire 1 E Cout $end
$var wire 1 D Cin $end
$scope module FA $end
$var wire 1 o A $end
$var wire 1 4 B $end
$var wire 1 E Cout $end
$var wire 1 2 S $end
$var wire 1 p w1 $end
$var wire 1 q w2 $end
$var wire 1 r w3 $end
$var wire 1 D Cin $end
$upscope $end
$upscope $end
$scope module cell_1_3 $end
$var wire 1 J Ain $end
$var wire 1 3 Bin $end
$var wire 1 s Din $end
$var wire 1 t w_add_A $end
$var wire 1 1 Sum $end
$var wire 1 D Cout $end
$var wire 1 C Cin $end
$scope module FA $end
$var wire 1 t A $end
$var wire 1 3 B $end
$var wire 1 D Cout $end
$var wire 1 1 S $end
$var wire 1 u w1 $end
$var wire 1 v w2 $end
$var wire 1 w w3 $end
$var wire 1 C Cin $end
$upscope $end
$upscope $end
$scope module cell_1_4 $end
$var wire 1 J Ain $end
$var wire 1 x Bin $end
$var wire 1 J Cin $end
$var wire 1 y Din $end
$var wire 1 z w_add_A $end
$var wire 1 0 Sum $end
$var wire 1 C Cout $end
$scope module FA $end
$var wire 1 z A $end
$var wire 1 x B $end
$var wire 1 J Cin $end
$var wire 1 C Cout $end
$var wire 1 0 S $end
$var wire 1 { w1 $end
$var wire 1 | w2 $end
$var wire 1 } w3 $end
$upscope $end
$upscope $end
$scope module cell_2_2 $end
$var wire 1 F Ain $end
$var wire 1 2 Bin $end
$var wire 1 ~ Din $end
$var wire 1 !" w_add_A $end
$var wire 1 7 Sum $end
$var wire 1 B Cout $end
$var wire 1 A Cin $end
$scope module FA $end
$var wire 1 !" A $end
$var wire 1 2 B $end
$var wire 1 B Cout $end
$var wire 1 7 S $end
$var wire 1 "" w1 $end
$var wire 1 #" w2 $end
$var wire 1 $" w3 $end
$var wire 1 A Cin $end
$upscope $end
$upscope $end
$scope module cell_2_3 $end
$var wire 1 F Ain $end
$var wire 1 1 Bin $end
$var wire 1 %" Din $end
$var wire 1 &" w_add_A $end
$var wire 1 / Sum $end
$var wire 1 A Cout $end
$var wire 1 @ Cin $end
$scope module FA $end
$var wire 1 &" A $end
$var wire 1 1 B $end
$var wire 1 A Cout $end
$var wire 1 / S $end
$var wire 1 '" w1 $end
$var wire 1 (" w2 $end
$var wire 1 )" w3 $end
$var wire 1 @ Cin $end
$upscope $end
$upscope $end
$scope module cell_2_4 $end
$var wire 1 F Ain $end
$var wire 1 0 Bin $end
$var wire 1 *" Din $end
$var wire 1 +" w_add_A $end
$var wire 1 . Sum $end
$var wire 1 @ Cout $end
$var wire 1 ? Cin $end
$scope module FA $end
$var wire 1 +" A $end
$var wire 1 0 B $end
$var wire 1 @ Cout $end
$var wire 1 . S $end
$var wire 1 ," w1 $end
$var wire 1 -" w2 $end
$var wire 1 ." w3 $end
$var wire 1 ? Cin $end
$upscope $end
$upscope $end
$scope module cell_2_5 $end
$var wire 1 F Ain $end
$var wire 1 /" Bin $end
$var wire 1 F Cin $end
$var wire 1 0" Din $end
$var wire 1 1" w_add_A $end
$var wire 1 - Sum $end
$var wire 1 ? Cout $end
$scope module FA $end
$var wire 1 1" A $end
$var wire 1 /" B $end
$var wire 1 F Cin $end
$var wire 1 ? Cout $end
$var wire 1 - S $end
$var wire 1 2" w1 $end
$var wire 1 3" w2 $end
$var wire 1 4" w3 $end
$upscope $end
$upscope $end
$scope module cell_3_3 $end
$var wire 1 B Ain $end
$var wire 1 / Bin $end
$var wire 1 5" Din $end
$var wire 1 6" w_add_A $end
$var wire 1 6 Sum $end
$var wire 1 > Cout $end
$var wire 1 = Cin $end
$scope module FA $end
$var wire 1 6" A $end
$var wire 1 / B $end
$var wire 1 > Cout $end
$var wire 1 6 S $end
$var wire 1 7" w1 $end
$var wire 1 8" w2 $end
$var wire 1 9" w3 $end
$var wire 1 = Cin $end
$upscope $end
$upscope $end
$scope module cell_3_4 $end
$var wire 1 B Ain $end
$var wire 1 . Bin $end
$var wire 1 :" Din $end
$var wire 1 ;" w_add_A $end
$var wire 1 , Sum $end
$var wire 1 = Cout $end
$var wire 1 < Cin $end
$scope module FA $end
$var wire 1 ;" A $end
$var wire 1 . B $end
$var wire 1 = Cout $end
$var wire 1 , S $end
$var wire 1 <" w1 $end
$var wire 1 =" w2 $end
$var wire 1 >" w3 $end
$var wire 1 < Cin $end
$upscope $end
$upscope $end
$scope module cell_3_5 $end
$var wire 1 B Ain $end
$var wire 1 - Bin $end
$var wire 1 ?" Din $end
$var wire 1 @" w_add_A $end
$var wire 1 + Sum $end
$var wire 1 < Cout $end
$var wire 1 ; Cin $end
$scope module FA $end
$var wire 1 @" A $end
$var wire 1 - B $end
$var wire 1 < Cout $end
$var wire 1 + S $end
$var wire 1 A" w1 $end
$var wire 1 B" w2 $end
$var wire 1 C" w3 $end
$var wire 1 ; Cin $end
$upscope $end
$upscope $end
$scope module cell_3_6 $end
$var wire 1 B Ain $end
$var wire 1 D" Bin $end
$var wire 1 B Cin $end
$var wire 1 E" Din $end
$var wire 1 F" w_add_A $end
$var wire 1 * Sum $end
$var wire 1 ; Cout $end
$scope module FA $end
$var wire 1 F" A $end
$var wire 1 D" B $end
$var wire 1 B Cin $end
$var wire 1 ; Cout $end
$var wire 1 * S $end
$var wire 1 G" w1 $end
$var wire 1 H" w2 $end
$var wire 1 I" w3 $end
$upscope $end
$upscope $end
$upscope $end
$upscope $end
$enddefinitions $end
$comment Show the parameter values. $end
$dumpall
$end
#0
$dumpvars
0I"
1H"
0G"
1F"
0E"
0D"
0C"
1B"
0A"
1@"
0?"
0>"
1="
0<"
1;"
0:"
09"
18"
07"
16"
05"
04"
13"
02"
11"
00"
0/"
0."
1-"
0,"
1+"
0*"
0)"
1("
0'"
1&"
0%"
0$"
1#"
0""
1!"
0~
0}
1|
0{
1z
0y
0x
0w
1v
0u
1t
0s
0r
1q
0p
1o
0n
0m
1l
0k
1j
0i
0h
1g
0f
1e
0d
1c
0b
1a
0`
1_
0^
1]
0\
0[
1Z
0Y
1X
0W
1V
0U
0T
1S
0R
1Q
0P
1O
0N
0M
1L
b1111 K
1J
1I
1H
1G
1F
1E
1D
1C
1B
1A
1@
1?
1>
1=
1<
1;
b0 :
09
08
07
06
05
04
03
02
01
00
0/
0.
0-
0,
0+
0*
b0 )
z(
b0 '
b0 &
z%
z$
b0 #
b0 "
b1111 !
$end
#10000
0>
0=
08"
06"
0;"
0@"
0B
0A
0="
0<
0#"
1+
0!"
0&"
0+"
0F
16
07"
09"
0E
0)"
1/
0("
0'"
0D
1,
0<"
0>"
0@
0l
0q
11
1.
0j
0o
0t
b0 !
b0 K
0J
0Q
19
0I
18
0k
0m
0X
15
17
0""
0$"
0H
12
0p
0r
0_
14
0v
0-"
0B"
0u
0G
0,"
0C
0A"
0?
0;
13
0g
10
0|
1-
03"
1*
0H"
0e
1z
11"
1F"
1d
1y
10"
1E"
b1 )
b1 #
b1 '
#20000
1G
0D
0@
0<
14
03
1g
11
0u
00
1.
0,"
0-
1+
0A"
0*
0]
1e
1t
0z
1+"
01"
1@"
0F"
1\
0d
1s
0y
1*"
00"
1?"
0E"
b10 )
b10 #
b10 '
#30000
1D
04
1@
1<
01
1u
0G
0.
1,"
0+
1A"
13
0g
10
1-
1*
0e
1z
11"
1F"
1d
1y
10"
1E"
b11 )
b11 #
b11 '
#40000
1H
1_
0p
1G
0E
0'"
0D
0A
0<"
0@
0=
0<
15
04
03
1g
12
0q
01
0u
00
1/
0("
0.
0,"
0-
1,
0="
0+
0A"
0*
0V
1]
1e
1o
0t
0z
1&"
0+"
01"
1;"
0@"
0F"
1U
0\
0d
1n
0s
0y
1%"
0*"
00"
1:"
0?"
0E"
b100 )
b100 #
b100 '
#50000
05
1E
1A
0H
02
1p
1=
0/
1'"
0_
14
0,
1<"
11
0G
1.
1+
13
0g
10
1-
1*
0e
1z
11"
1F"
1d
1y
10"
1E"
b101 )
b101 #
b101 '
#60000
0q
0("
0="
1p
1G
1'"
0D
1<"
0@
0<
14
03
1g
11
0u
00
1.
0,"
0-
1+
0A"
0*
0]
1e
1t
0z
1+"
01"
1@"
0F"
1\
0d
1s
0y
1*"
00"
1?"
0E"
b110 )
b110 #
b110 '
#70000
1q
0p
1("
1="
0'"
1D
04
0<"
1@
1<
01
1u
0G
0.
1,"
0+
1A"
13
0g
10
1-
1*
0e
1z
11"
1F"
1d
1y
10"
1E"
b111 )
b111 #
b111 '
#80000
1>
18"
1B"
1G"
1H"
1;
16"
1*
1I"
1B
1#"
1-"
1?
13"
1!"
1F
1l
1v
1C
1|
1j
b1111 !
b1111 K
1J
1Q
09
1I
08
1X
07
06
1H
1_
1G
1E
1D
1A
1@
1=
1<
05
04
03
1g
02
1q
01
0u
00
0/
1("
0.
0,"
0-
0,
1="
0+
0A"
1V
1]
1e
1o
1t
1z
1&"
1+"
11"
1;"
1@"
1F"
1D"
0U
0\
0d
0n
0s
0y
0%"
0*"
00"
0:"
0?"
0E"
b1 :
b1 "
b1 &
b0 )
b0 #
b0 '
#90000
1>
1=
1<
08"
0="
0B"
1;
06"
0;"
0@"
0I"
0B
0A
0#"
0!"
0&"
0+"
0F
06
07"
19"
0E
0)"
1/
0("
0'"
0D
0,
0<"
1>"
0@
0l
0q
11
1.
0j
0o
0t
b1 !
b1 K
0J
0Q
19
0I
18
0k
0m
0X
15
17
0""
0$"
0H
12
0p
0r
0_
14
0v
0-"
0u
0G
0,"
0C
0+
0A"
1C"
0?
13
0g
10
0|
1-
03"
0*
1G"
0H"
0e
1z
11"
1F"
1d
1y
10"
1E"
b1 )
b1 #
b1 '
#100000
b0 !
b0 K
0>
09"
16
0=
0<
1G
0D
1,
0>"
0@
0C"
0;
14
03
1g
11
0u
00
1.
0,"
0-
1+
0A"
0B"
1*
0G"
0]
1e
1t
0z
1+"
01"
1@"
0F"
1\
0d
1s
0y
1*"
00"
1?"
0E"
b10 )
b10 #
b10 '
#110000
1D
04
1@
1<
1B"
01
1u
0G
0.
1,"
1A"
1C"
1;
13
0g
10
1-
0*
1G"
0e
1z
11"
1F"
1d
1y
10"
1E"
b11 )
b11 #
b11 '
#120000
1H
1_
0<
0p
1G
0E
0'"
0D
0A
0<"
0>"
0@
0C"
0=
0;
15
04
03
1g
12
0q
01
0u
00
1/
0("
0.
0,"
0-
1,
0="
0+
0A"
0B"
1*
0G"
0V
1]
1e
1o
0t
0z
1&"
0+"
01"
1;"
0@"
0F"
1U
0\
0d
1n
0s
0y
1%"
0*"
00"
1:"
0?"
0E"
b100 )
b100 #
b100 '
#130000
05
1E
1A
0H
02
1p
1=
1="
0/
1'"
0_
14
1<"
1>"
1<
11
0G
1.
1C"
1;
13
0g
10
1-
0*
1G"
0e
1z
11"
1F"
1d
1y
10"
1E"
b101 )
b101 #
b101 '
#140000
0="
0q
0("
0<
1p
1G
1'"
0D
0,
1<"
0>"
0@
0C"
0;
14
03
1g
11
0u
00
1.
0,"
0-
1+
0A"
0B"
1*
0G"
0]
1e
1t
0z
1+"
01"
1@"
0F"
1\
0d
1s
0y
1*"
00"
1?"
0E"
b110 )
b110 #
b110 '
#150000
1q
0p
1("
1="
0'"
1D
04
0<"
1@
1<
1B"
01
1u
0G
0.
1,"
1A"
1C"
1;
13
0g
10
1-
0*
1G"
0e
1z
11"
1F"
1d
1y
10"
1E"
b111 )
b111 #
b111 '
#160000
1>
18"
1H"
16"
0*
1B
1#"
1-"
12"
13"
1?
1!"
1-
14"
1F
1l
1v
1C
1|
1j
b1111 !
b1111 K
1J
1Q
09
1I
08
1X
07
06
1H
1<
1_
1C"
1G
1E
1D
1A
0>"
1@
1=
1;
05
04
03
1g
02
1q
01
0u
00
0/
1("
0.
0,"
0,
1="
1+
1A"
1B"
0G"
1V
1]
1e
1o
1t
1z
1&"
1+"
11"
1;"
1@"
1F"
1/"
0D"
0U
0\
0d
0n
0s
0y
0%"
0*"
00"
0:"
0?"
0E"
b10 :
b10 "
b10 &
b0 )
b0 #
b0 '
#170000
16"
1;"
1@"
0>
1B
1A
0>"
1@
0#"
0("
0-"
1+
1?
0!"
0&"
0+"
04"
0F
09"
16
0E
08"
07"
0=
0/
0'"
1)"
0D
1,
0l
0q
11
0j
0o
0t
b10 !
b10 K
0J
0Q
19
0I
18
0k
0m
0X
15
07
0""
1$"
0H
12
0p
0r
0="
0_
14
0<"
0v
0<
0B"
0u
0G
0.
0,"
1."
0C
0A"
0C"
0;
13
0g
10
0|
0-
12"
03"
1*
0H"
0e
1z
11"
0F"
1d
1y
10"
1E"
b1 )
b1 #
b1 '
#180000
06
1A"
06"
0;"
0B
b1 !
b1 K
1>
0$"
17
08"
1>"
0="
07"
19"
0A
0@
1=
1<
1G
1/
0)"
0D
0."
0,
0<"
0C"
0?
0;
14
03
1g
11
0u
00
1.
0,"
0-"
1-
02"
0+
0*
0H"
0]
1e
1t
0z
1+"
01"
1@"
0F"
1\
0d
1s
0y
1*"
00"
1?"
0E"
b10 )
b10 #
b10 '
#190000
b0 !
b0 K
0>
09"
16
0=
0>"
1,
1D
04
1@
0<
1-"
01
1u
0G
1,"
1."
1+
0A"
1?
13
0g
10
0-
12"
1*
0e
1z
11"
1F"
1d
1y
10"
1E"
b11 )
b11 #
b11 '
#200000
1H
1_
0@
0p
1G
0E
0'"
0)"
0D
0."
0A
0?
0=
15
04
03
1g
12
0q
01
0u
00
1/
0("
0.
0,"
0-"
1-
02"
1,
0<"
1+
0*
0V
1]
1e
1o
0t
0z
1&"
0+"
01"
1;"
0@"
0F"
1U
0\
0d
1n
0s
0y
1%"
0*"
00"
1:"
0?"
0E"
b100 )
b100 #
b100 '
#210000
05
1E
1A
0H
02
1p
1("
1'"
1)"
0_
14
1@
11
0G
1."
0+
1?
13
0g
10
0-
12"
1*
0e
1z
11"
1F"
1d
1y
10"
1E"
b101 )
b101 #
b101 '
#220000
0("
1>"
1="
0q
0@
1=
1<
1p
1G
0/
1'"
0)"
0D
0."
1,
1<"
1A"
0?
14
03
1g
11
0u
00
1.
0,"
0-"
1-
02"
0+
0*
0]
1e
1t
0z
1+"
01"
1@"
0F"
1\
0d
1s
0y
1*"
00"
1?"
0E"
b110 )
b110 #
b110 '
#230000
1q
0p
1("
0>"
0="
0,
0'"
1D
04
1@
0<
1-"
01
1u
0G
1,"
1."
1+
0A"
1?
13
0g
10
0-
12"
1*
0e
1z
11"
1F"
1d
1y
10"
1E"
b111 )
b111 #
b111 '
#240000
1>
18"
1="
1H"
1#"
13"
1!"
14"
1F
1l
1v
1C
1|
1j
1J
1<
1C"
1Q
09
1A"
1B"
1G"
1;
1I
08
16"
1*
1I"
1X
b1111 !
b1111 K
1B
1H
0$"
07
1_
06
1@
1G
1E
0)"
1D
0."
1A
1?
1=
05
04
03
1g
02
1q
01
0u
00
0/
1("
0.
0,"
1-"
1-
12"
0,
0<"
1+
1V
1]
1e
1o
1t
1z
1&"
1+"
11"
1;"
1@"
1F"
1D"
0U
0\
0d
0n
0s
0y
0%"
0*"
00"
0:"
0?"
0E"
b11 :
b11 "
b11 &
b0 )
b0 #
b0 '
#250000
1>
1=
1<
18"
1="
1B"
1;
16"
1;"
1@"
1I"
1B
1A
1@
0#"
0("
0-"
1?
0!"
0&"
0+"
04"
0F
0E
06
07"
09"
0/
0'"
1)"
0D
0l
0q
11
0j
0o
0t
b11 !
b11 K
0J
0Q
19
0I
18
0k
0m
0X
15
07
0""
1$"
0H
12
0p
0r
0_
14
0,
0<"
0>"
0v
0u
0G
0.
0,"
1."
0C
0+
0A"
0C"
13
0g
10
0|
0-
12"
03"
0*
0G"
0H"
0e
1z
11"
0F"
1d
1y
10"
1E"
b1 )
b1 #
b1 '
#260000
0;
08"
1A"
06"
0;"
0I"
b1 !
b1 K
0B
0$"
17
1>"
0,
06
07"
19"
0A
0@
0="
1G
1/
0)"
0D
0."
0<"
0C"
0?
1<
14
03
1g
11
0u
00
1.
0,"
0-"
1-
02"
0+
0B"
1*
0G"
0H"
0]
1e
1t
0z
1+"
01"
1@"
0F"
1\
0d
1s
0y
1*"
00"
1?"
0E"
b10 )
b10 #
b10 '
#270000
1D
04
1@
1-"
1B"
01
1u
0G
1,"
1."
0A"
1?
1;
13
0g
10
0-
12"
0*
1G"
0e
1z
11"
1F"
1d
1y
10"
1E"
b11 )
b11 #
b11 '
#280000
1H
1_
0@
b0 !
b0 K
0>
0=
0p
1G
0E
0'"
0)"
0D
0."
16
09"
0A
0>"
0?
0<
0;
15
04
03
1g
12
0q
01
0u
00
1/
0("
0.
0,"
0-"
1-
02"
1,
0<"
0="
1+
0B"
1*
0G"
0V
1]
1e
1o
0t
0z
1&"
0+"
01"
1;"
0@"
0F"
1U
0\
0d
1n
0s
0y
1%"
0*"
00"
1:"
0?"
0E"
b100 )
b100 #
b100 '
#290000
05
1E
1A
0H
02
1p
1("
1'"
1)"
0_
14
1@
11
0G
1."
1?
1;
13
0g
10
0-
12"
0*
1G"
0e
1z
11"
1F"
1d
1y
10"
1E"
b101 )
b101 #
b101 '
#300000
0("
0q
0@
1=
1="
1p
1G
0/
1'"
0)"
0D
0."
1<"
1>"
1A"
0?
1<
0;
14
03
1g
11
0u
00
1.
0,"
0-"
1-
02"
0+
0B"
1*
0G"
0]
1e
1t
0z
1+"
01"
1@"
0F"
1\
0d
1s
0y
1*"
00"
1?"
0E"
b110 )
b110 #
b110 '
#310000
1q
0p
1("
0'"
1D
04
1@
1-"
1B"
01
1u
0G
1,"
1."
0A"
1?
1;
13
0g
10
0-
12"
0*
1G"
0e
1z
11"
1F"
1d
1y
10"
1E"
b111 )
b111 #
b111 '
#320000
18"
1H"
1#"
13"
1!"
0-
1F
1l
1v
1{
1|
1C
1j
10
1}
1J
1Q
09
1I
08
16"
0*
1X
1B
1H
0$"
07
1@
1_
b1111 !
b1111 K
1>
1=
1."
1G
1E
0)"
1D
06
09"
1A
1>"
1<
1?
1;
05
04
03
1g
02
1q
01
0u
0/
1("
1.
1,"
1-"
1,
1<"
1="
0+
1B"
02"
0G"
1V
1]
1e
1o
1t
1z
1&"
1+"
11"
1;"
1@"
1F"
1x
0/"
0D"
0U
0\
0d
0n
0s
0y
0%"
0*"
00"
0:"
0?"
0E"
b100 :
b100 "
b100 &
b0 )
b0 #
b0 '
#330000
0C"
1+
0>
0=
0<
08"
0="
06"
0;"
0@"
1!"
1&"
1+"
0B
1F
0#"
0A
1E
16
07"
09"
0)"
1/
1D
1,
0<"
0>"
0l
0q
0v
1.
1C
0j
0o
0t
0}
b100 !
b100 K
0J
0Q
19
0I
08
0k
1m
0X
15
17
0""
0$"
0H
02
0p
1r
0("
0'"
0_
14
0@
0-"
0B"
01
0u
1w
0G
0,"
0."
0A"
0?
0;
13
0g
00
1{
0|
1-
03"
1*
0H"
0e
1z
01"
1F"
1d
1y
10"
1E"
b1 )
b1 #
b1 '
#340000
0>
1;
07
1,"
07"
1H"
0!"
0&"
16"
1;"
0F
b10 !
b10 K
1B
0m
18
0#"
1)"
0("
1,
0""
1$"
0E
0D
16
1A
1@
12
0r
0w
1G
0/
0'"
0."
0C
0?
0<
14
03
1g
11
0u
0v
10
0{
0.
0-
03"
1+
0A"
0*
0]
1e
1t
0z
1+"
01"
0@"
1F"
1\
0d
1s
0y
1*"
00"
1?"
0E"
b10 )
b10 #
b10 '
#350000
1>"
1<
06
0+
1A"
06"
0;"
1@"
0B
0$"
17
b1 !
b1 K
1>
08"
0A
07"
19"
1=
0)"
1/
1D
04
0,
0<"
0@
1v
1u
1w
0G
1.
0,"
1C
0;
13
0g
00
1{
1-
1*
0H"
0e
1z
11"
1F"
1d
1y
10"
1E"
b11 )
b11 #
b11 '
#360000
1H
0D
1_
b1 !
b1 K
1>
1=
0p
0r
0w
1G
0E
0C
06
19"
0A
0>"
0<
15
04
03
1g
12
0q
01
0u
0v
10
0{
1/
0'"
1.
0-
0,
1<"
0="
0+
0A"
0*
0V
1]
1e
1o
0t
0z
1&"
0+"
01"
1;"
0@"
0F"
1U
0\
0d
1n
0s
0y
1%"
0*"
00"
1:"
0?"
0E"
b100 )
b100 #
b100 '
