Wallace Tree/full_adder.v
module  full_adder(S, Cout, A, B, Cin);
    input A, B, Cin;
    output S, Cout;
    wire w1, w2, w3;
    
    xor Sresults(S, A, B, Cin);
    and A_and_B(w1, A, B);
    and A_and_Cin(w2, A, Cin);
    and B_and_Cin(w3, B, Cin);
    or Cresults(Cout, w1, w2, w3);

endmodule

Wallace Tree/wallace_4b.v
module wallace_tree_4b(result, data_operandA, data_operandB);

input [3:0] data_operandA, data_operandB;
output [7:0] result;

//row 0

// wirename row_column
wire w_0_0, w_0_1, w_0_2, w_0_3;

assign w_0_0 = data_operandA[0] & data_operandB[0];
assign w_0_1 = data_operandA[1] & data_operandB[0];
assign w_0_2 = data_operandA[2] & data_operandB[0];
assign w_0_3 = ~(data_operandA[3] & data_operandB[0]);

assign result[0] = w_0_0;

//row 1
wire w_1_1, w_1_2, w_1_3, w_1_4;
wire s_1_1, s_1_2, s_1_3, s_1_4;
wire c_1_1, c_1_2, c_1_3, c_1_4;

assign w_1_1 = data_operandA[0] & data_operandB[1];
assign w_1_2 = data_operandA[1] & data_operandB[1];
assign w_1_3 = data_operandA[2] & data_operandB[1];
assign w_1_4 = ~(data_operandA[3] & data_operandB[1]);

full_adder adder_1_1(.S(s_1_1), .Cout(c_1_1), .A(w_0_1), .B(w_1_1), .Cin(1'b0));
full_adder adder_1_2(.S(s_1_2), .Cout(c_1_2), .A(w_0_2), .B(w_1_2), .Cin(c_1_1));
full_adder adder_1_3(.S(s_1_3), .Cout(c_1_3), .A(w_0_3), .B(w_1_3), .Cin(c_1_2));
full_adder adder_1_4(.S(s_1_4), .Cout(c_1_4), .A(1'b1), .B(w_1_4), .Cin(c_1_3));

assign result[1] = s_1_1;

//row 2
wire w_2_2, w_2_3, w_2_4, w_2_5;
wire s_2_2, s_2_3, s_2_4, s_2_5;
wire c_2_2, c_2_3, c_2_4, c_2_5;

assign w_2_2 = data_operandA[0] & data_operandB[2];
assign w_2_3 = data_operandA[1] & data_operandB[2];
assign w_2_4 = data_operandA[2] & data_operandB[2];
assign w_2_5 = ~(data_operandA[3] & data_operandB[2]);

full_adder adder_2_2(.S(s_2_2), .Cout(c_2_2), .A(s_1_2), .B(w_2_2), .Cin(1'b0));
full_adder adder_2_3(.S(s_2_3), .Cout(c_2_3), .A(s_1_3), .B(w_2_3), .Cin(c_2_2));
full_adder adder_2_4(.S(s_2_4), .Cout(c_2_4), .A(s_1_4), .B(w_2_4), .Cin(c_2_3));
full_adder adder_2_5(.S(s_2_5), .Cout(c_2_5), .A(c_1_4), .B(w_2_5), .Cin(c_2_4));

assign result[2] = s_2_2;

//row 3 (final row)
wire w_3_3, w_3_4, w_3_5, w_3_6;
wire s_3_3, s_3_4, s_3_5, s_3_6, s_3_7;
wire c_3_3, c_3_4, c_3_5, c_3_6, c_3_7;

assign w_3_3 = ~(data_operandA[0] & data_operandB[3]);
assign w_3_4 = ~(data_operandA[1] & data_operandB[3]);
assign w_3_5 = ~(data_operandA[2] & data_operandB[3]);
assign w_3_6 = data_operandA[3] & data_operandB[3];

full_adder adder_3_3(.S(s_3_3), .Cout(c_3_3), .A(s_2_3), .B(w_3_3), .Cin(1'b0));
full_adder adder_3_4(.S(s_3_4), .Cout(c_3_4), .A(s_2_4), .B(w_3_4), .Cin(c_3_3));
full_adder adder_3_5(.S(s_3_5), .Cout(c_3_5), .A(s_2_5), .B(w_3_5), .Cin(c_3_4));
full_adder adder_3_6(.S(s_3_6), .Cout(c_3_6), .A(c_2_5), .B(w_3_6), .Cin(c_3_5));
full_adder adder_3_7(.S(s_3_7), .Cout(c_3_7), .A(1'b1), .B(c_3_6), .Cin(1'b0));

assign result[3] = s_3_3;
assign result[4] = s_3_4;
assign result[5] = s_3_5;
assign result[6] = s_3_6;
assign result[7] = s_3_7;


endmodule

Wallace Tree/wallace_4b_tb.v
`timescale 1ns / 1ps

module wallace_4b_tb;

reg signed [3:0] data_operandA, data_operandB; // Use signed for two's complement
wire signed [7:0] data_result; // Use signed for two's complement

// Instance of wallaceTree module
wallace_tree_4b uut (
    .data_operandA(data_operandA),
    .data_operandB(data_operandB),
    .result(data_result)
);

initial begin
    // Initialize inputs in two's complement
    data_operandA = 4'sb0000;
    data_operandB = 4'sb0000;

    $dumpfile("wallace_4b_tb.vcd");
    $dumpvars(0, wallace_4b_tb);

    // Iterate through all possible input combinations
    repeat (8) begin
        data_operandB = 4'sd0; // Reset data_operandB for each new data_operandA value
        repeat (8) begin
            #10; // Wait 10 time units; adjust this delay as needed
            data_operandB = data_operandB + 4'sd1;
        end
        data_operandA = data_operandA + 4'sd1;
    end

    data_operandA = 4'sd0;
    data_operandB = 4'sd0;
    repeat (8) begin
        data_operandB = 4'sd0; // Reset data_operandB for each new data_operandA value
        repeat (8) begin
            #10; // Wait 10 time units; adjust this delay as needed
            data_operandB = data_operandB - 4'sd1;
        end
        data_operandA = data_operandA - 4'sd1;
    end

    data_operandA = 4'sd0;
    data_operandB = 4'sd0;
    repeat (8) begin
        data_operandB = 4'sd0; // Reset data_operandB for each new data_operandA value
        repeat (8) begin
            #10; // Wait 10 time units; adjust this delay as needed
            data_operandB = data_operandB + 4'sd1;
        end
        data_operandA = data_operandA - 4'sd1;
    end

    data_operandA = 4'sd0;
    data_operandB = 4'sd0;
    repeat (8) begin
        data_operandB = 4'sd0; // Reset data_operandB for each new data_operandA value
        repeat (8) begin
            #10; // Wait 10 time units; adjust this delay as needed
            data_operandB = data_operandB - 4'sd1;
        end
        data_operandA = data_operandA + 4'sd1;
    end
    
    #10; // Wait for the last operation to complete
    $finish; // End the simulation
end

// Optional: Display test results
initial begin
    $monitor("At time %t, data_operandA = %d, data_operandB = %d, data_result = %d",
             $time, data_operandA, data_operandB, data_result);
end

endmodule

Wallace Tree/wallace_4b_tb.vcd
$date
	Fri Feb  9 19:15:19 2024
$end
$version
	Icarus Verilog
$end
$timescale
	1ps
$end
$scope module wallace_4b_tb $end
$var wire 8 ! data_result [7:0] $end
$var reg 4 " data_operandA [3:0] $end
$var reg 4 # data_operandB [3:0] $end
$scope module uut $end
$var wire 4 $ data_operandA [3:0] $end
$var wire 4 % data_operandB [3:0] $end
$var wire 1 & w_0_0 $end
$var wire 1 ' w_0_1 $end
$var wire 1 ( w_0_2 $end
$var wire 1 ) w_0_3 $end
$var wire 1 * w_1_1 $end
$var wire 1 + w_1_2 $end
$var wire 1 , w_1_3 $end
$var wire 1 - w_1_4 $end
$var wire 1 . w_2_2 $end
$var wire 1 / w_2_3 $end
$var wire 1 0 w_2_4 $end
$var wire 1 1 w_2_5 $end
$var wire 1 2 w_3_3 $end
$var wire 1 3 w_3_4 $end
$var wire 1 4 w_3_5 $end
$var wire 1 5 w_3_6 $end
$var wire 1 6 s_3_7 $end
$var wire 1 7 s_3_6 $end
$var wire 1 8 s_3_5 $end
$var wire 1 9 s_3_4 $end
$var wire 1 : s_3_3 $end
$var wire 1 ; s_2_5 $end
$var wire 1 < s_2_4 $end
$var wire 1 = s_2_3 $end
$var wire 1 > s_2_2 $end
$var wire 1 ? s_1_4 $end
$var wire 1 @ s_1_3 $end
$var wire 1 A s_1_2 $end
$var wire 1 B s_1_1 $end
$var wire 8 C result [7:0] $end
$var wire 1 D c_3_7 $end
$var wire 1 E c_3_6 $end
$var wire 1 F c_3_5 $end
$var wire 1 G c_3_4 $end
$var wire 1 H c_3_3 $end
$var wire 1 I c_2_5 $end
$var wire 1 J c_2_4 $end
$var wire 1 K c_2_3 $end
$var wire 1 L c_2_2 $end
$var wire 1 M c_1_4 $end
$var wire 1 N c_1_3 $end
$var wire 1 O c_1_2 $end
$var wire 1 P c_1_1 $end
$scope module adder_1_1 $end
$var wire 1 ' A $end
$var wire 1 * B $end
$var wire 1 Q Cin $end
$var wire 1 P Cout $end
$var wire 1 B S $end
$var wire 1 R w1 $end
$var wire 1 S w2 $end
$var wire 1 T w3 $end
$upscope $end
$scope module adder_1_2 $end
$var wire 1 ( A $end
$var wire 1 + B $end
$var wire 1 P Cin $end
$var wire 1 O Cout $end
$var wire 1 A S $end
$var wire 1 U w1 $end
$var wire 1 V w2 $end
$var wire 1 W w3 $end
$upscope $end
$scope module adder_1_3 $end
$var wire 1 ) A $end
$var wire 1 , B $end
$var wire 1 O Cin $end
$var wire 1 N Cout $end
$var wire 1 @ S $end
$var wire 1 X w1 $end
$var wire 1 Y w2 $end
$var wire 1 Z w3 $end
$upscope $end
$scope module adder_1_4 $end
$var wire 1 [ A $end
$var wire 1 - B $end
$var wire 1 N Cin $end
$var wire 1 M Cout $end
$var wire 1 ? S $end
$var wire 1 \ w1 $end
$var wire 1 ] w2 $end
$var wire 1 ^ w3 $end
$upscope $end
$scope module adder_2_2 $end
$var wire 1 A A $end
$var wire 1 . B $end
$var wire 1 _ Cin $end
$var wire 1 L Cout $end
$var wire 1 > S $end
$var wire 1 ` w1 $end
$var wire 1 a w2 $end
$var wire 1 b w3 $end
$upscope $end
$scope module adder_2_3 $end
$var wire 1 @ A $end
$var wire 1 / B $end
$var wire 1 L Cin $end
$var wire 1 K Cout $end
$var wire 1 = S $end
$var wire 1 c w1 $end
$var wire 1 d w2 $end
$var wire 1 e w3 $end
$upscope $end
$scope module adder_2_4 $end
$var wire 1 ? A $end
$var wire 1 0 B $end
$var wire 1 K Cin $end
$var wire 1 J Cout $end
$var wire 1 < S $end
$var wire 1 f w1 $end
$var wire 1 g w2 $end
$var wire 1 h w3 $end
$upscope $end
$scope module adder_2_5 $end
$var wire 1 M A $end
$var wire 1 1 B $end
$var wire 1 J Cin $end
$var wire 1 I Cout $end
$var wire 1 ; S $end
$var wire 1 i w1 $end
$var wire 1 j w2 $end
$var wire 1 k w3 $end
$upscope $end
$scope module adder_3_3 $end
$var wire 1 = A $end
$var wire 1 2 B $end
$var wire 1 l Cin $end
$var wire 1 H Cout $end
$var wire 1 : S $end
$var wire 1 m w1 $end
$var wire 1 n w2 $end
$var wire 1 o w3 $end
$upscope $end
$scope module adder_3_4 $end
$var wire 1 < A $end
$var wire 1 3 B $end
$var wire 1 H Cin $end
$var wire 1 G Cout $end
$var wire 1 9 S $end
$var wire 1 p w1 $end
$var wire 1 q w2 $end
$var wire 1 r w3 $end
$upscope $end
$scope module adder_3_5 $end
$var wire 1 ; A $end
$var wire 1 4 B $end
$var wire 1 G Cin $end
$var wire 1 F Cout $end
$var wire 1 8 S $end
$var wire 1 s w1 $end
$var wire 1 t w2 $end
$var wire 1 u w3 $end
$upscope $end
$scope module adder_3_6 $end
$var wire 1 I A $end
$var wire 1 5 B $end
$var wire 1 F Cin $end
$var wire 1 E Cout $end
$var wire 1 7 S $end
$var wire 1 v w1 $end
$var wire 1 w w2 $end
$var wire 1 x w3 $end
$upscope $end
$scope module adder_3_7 $end
$var wire 1 y A $end
$var wire 1 E B $end
$var wire 1 z Cin $end
$var wire 1 D Cout $end
$var wire 1 6 S $end
$var wire 1 { w1 $end
$var wire 1 | w2 $end
$var wire 1 } w3 $end
$upscope $end
$upscope $end
$upscope $end
$enddefinitions $end
$comment Show the parameter values. $end
$dumpall
$end
#0
$dumpvars
0}
0|
1{
0z
1y
0x
1w
0v
1u
0t
0s
1r
0q
0p
0o
0n
1m
0l
0k
0j
1i
0h
0g
0f
0e
0d
0c
0b
0a
0`
0_
0^
0]
1\
1[
0Z
0Y
0X
0W
0V
0U
0T
0S
0R
0Q
0P
0O
0N
1M
0L
0K
0J
1I
1H
1G
1F
1E
1D
b0 C
0B
0A
1@
0?
0>
1=
0<
0;
0:
09
08
07
06
05
14
13
12
11
00
0/
0.
1-
0,
0+
0*
1)
0(
0'
0&
b0 %
b0 $
b0 #
b0 "
b0 !
$end
#10000
b1 #
b1 %
#20000
b10 #
b10 %
#30000
b11 #
b11 %
#40000
b100 #
b100 %
#50000
b101 #
b101 %
#60000
b110 #
b110 %
#70000
b111 #
b111 %
#80000
b1 "
b1 $
b0 #
b0 %
#90000
b1 !
b1 C
1&
b1 #
b1 %
#100000
1B
b10 !
b10 C
0&
1*
b10 #
b10 %
#110000
b11 !
b11 C
1&
b11 #
b11 %
#120000
0B
1>
b100 !
b100 C
0&
0*
1.
b100 #
b100 %
#130000
b101 !
b101 C
1&
b101 #
b101 %
#140000
1B
b110 !
b110 C
0&
1*
b110 #
b110 %
#150000
b111 !
b111 C
1&
b111 #
b111 %
#160000
0B
0>
b0 !
b0 C
0&
0*
0.
b10 "
b10 $
b0 #
b0 %
#170000
b10 !
b10 C
1B
1'
b1 #
b1 %
#180000
1>
b100 !
b100 C
0B
1A
0'
1+
b10 #
b10 %
#190000
b110 !
b110 C
1B
1'
b11 #
b11 %
#200000
0r
1p
0H
1<
0>
1:
0m
1K
b1000 !
b1000 C
0B
0A
0=
1c
0'
0+
1/
b100 #
b100 %
#210000
b1010 !
b1010 C
1B
1'
b101 #
b101 %
#220000
1>
b1100 !
b1100 C
0B
1A
0'
1+
b110 #
b110 %
#230000
b1110 !
b1110 C
1B
1'
b111 #
b111 %
#240000
1r
0p
1H
0<
0>
0:
1m
0K
b0 !
b0 C
0B
0A
1=
0c
0'
0+
0/
b11 "
b11 $
b0 #
b0 %
#250000
1B
b11 !
b11 C
1&
1'
b1 #
b1 %
#260000
1>
1A
b110 !
b110 C
0&
0'
1*
1+
b10 #
b10 %
#270000
0r
1p
0H
1<
1:
0m
1?
1]
1^
0=
1N
0@
1Y
0>
1O
0A
1W
1P
0B
1R
b1001 !
b1001 C
1&
1'
b11 #
b11 %
#280000
1K
0?
0]
0^
0e
1c
0d
0N
09
0q
0r
0L
1@
0Y
0H
0P
0`
0O
1:
0m
0R
0A
0W
1>
0=
b1100 !
b1100 C
0&
0'
0*
0+
1.
1/
b100 #
b100 %
#290000
1B
b1111 !
b1111 C
1&
1'
b101 #
b101 %
#300000
19
1q
1r
1H
0:
1m
1=
1d
1e
1L
0>
1`
1A
b10010 !
b10010 C
0&
0'
1*
1+
b110 #
b110 %
#310000
0K
1?
1]
1^
0e
0c
0d
1N
0L
0@
1Y
1>
0`
1O
0A
1W
1P
0B
1R
b10101 !
b10101 C
1&
1'
b111 #
b111 %
#320000
0p
0<
0?
0]
0^
0N
09
0q
1r
1@
0Y
1H
0P
0O
0:
1m
0R
0A
0W
0>
1=
b0 !
b0 C
0&
0'
0*
0+
0.
0/
b100 "
b100 $
b0 #
b0 %
#330000
b100 !
b100 C
1>
1A
1(
b1 #
b1 %
#340000
0r
1p
0H
1<
1:
0m
1?
1]
1^
b1000 !
b1000 C
0>
0=
1N
0A
0@
1X
0(
1,
b10 #
b10 %
#350000
b1100 !
b1100 C
1>
1A
1(
b11 #
b11 %
#360000
1r
1q
1H
1u
0s
0:
1m
0?
0]
0^
1G
0;
0j
0k
0>
1=
0N
b10000 !
b10000 C
19
1p
0J
0A
1@
0X
1<
0f
0(
0,
10
b100 #
b100 %
#370000
b10100 !
b10100 C
1>
1A
1(
b101 #
b101 %
#380000
0u
1s
0G
1;
1j
1k
0r
0p
0q
1J
0H
0<
1f
1:
0m
1?
1]
1^
b11000 !
b11000 C
0>
0=
1N
0A
0@
1X
0(
1,
b110 #
b110 %
#390000
b11100 !
b11100 C
1>
1A
1(
b111 #
b111 %
#400000
1r
1H
1u
0s
0:
1m
0?
0]
0^
1G
0;
0j
0k
0>
1=
0N
b0 !
b0 C
09
0p
0J
0A
1@
0X
0<
0f
0(
0,
00
b101 "
b101 $
b0 #
b0 %
#410000
1>
1A
b101 !
b101 C
1&
1(
b1 #
b1 %
#420000
0r
1p
0H
1<
1:
0m
1?
1]
1^
0>
0=
1N
0A
1B
0@
1X
b1010 !
b1010 C
0&
0(
1*
1,
b10 #
b10 %
#430000
1>
1A
b1111 !
b1111 C
1&
1(
b11 #
b11 %
#440000
1r
1q
1H
0:
1m
1=
0h
1u
0s
0K
0?
0]
0^
1G
0;
0j
0k
0d
0N
0L
19
1p
0J
0A
0B
1@
0X
1>
0`
1<
0f
b10100 !
b10100 C
0&
0(
0*
0,
1.
10
b100 #
b100 %
#450000
0u
1s
0G
1;
1j
1k
0r
0p
0q
1J
0H
0<
1h
1:
0m
1K
0=
1d
1L
0>
1`
1A
b11001 !
b11001 C
1&
1(
b101 #
b101 %
#460000
08
0t
0u
0G
19
0r
0H
0h
1f
0L
1:
0m
0K
1?
1]
1^
1>
0`
0=
0d
1N
0A
1B
0@
1X
b11110 !
b11110 C
0&
0(
1*
1,
b110 #
b110 %
#470000
18
1t
1u
1G
09
1r
1H
0:
1m
1=
1L
0>
1`
1A
b100011 !
b100011 C
1&
1(
b111 #
b111 %
#480000
08
0s
0t
0?
0]
0^
0;
0j
0k
0N
0L
09
0p
0q
0J
0A
0B
1@
0X
0>
0`
0<
0f
b0 !
b0 C
0&
0(
0*
0,
0.
00
b110 "
b110 $
b0 #
b0 %
#490000
1>
b110 !
b110 C
1B
1A
1'
1(
b1 #
b1 %
#500000
0r
1p
0H
1<
1:
0m
1?
1]
1^
0=
1N
b1100 !
b1100 C
0B
0@
1X
0'
0(
1+
1,
b10 #
b10 %
#510000
19
1q
1r
1H
0:
1m
1=
1@
1Y
1Z
0>
1O
b10010 !
b10010 C
1B
0A
1U
1'
1(
b11 #
b11 %
#520000
0u
0G
0?
0]
0^
0N
0r
08
1s
0t
0Y
0H
0g
1h
1;
1j
1k
0O
1:
0m
1K
19
0p
0q
1J
b11000 !
b11000 C
0B
0U
1@
0X
0Z
0=
1c
0<
0f
0'
0(
0+
0,
1/
10
b100 #
b100 %
#530000
1>
b11110 !
b11110 C
1B
1A
1'
1(
b101 #
b101 %
#540000
18
1t
1u
1G
09
1r
1H
0h
1f
0:
1m
0K
1?
1]
1^
1=
0c
1N
b100100 !
b100100 C
0B
0@
1X
0'
0(
1+
1,
b110 #
b110 %
#550000
0r
1p
0H
1<
1g
1h
1:
0m
1K
0=
1c
1@
1Y
1Z
0>
1O
b101010 !
b101010 C
1B
0A
1U
1'
1(
b111 #
b111 %
#560000
0s
0?
0]
0^
0;
0j
0k
0N
1r
0q
0J
08
0t
1u
0Y
1H
0g
1G
0O
0:
1m
0K
09
0p
b0 !
b0 C
0B
0U
1@
0X
0Z
1=
0c
0<
0f
0h
0'
0(
0+
0,
0/
00
b111 "
b111 $
b0 #
b0 %
#570000
1>
1B
1A
b111 !
b111 C
1&
1'
1(
b1 #
b1 %
#580000
0r
1p
0H
1<
1:
0m
1?
1]
1^
0=
1N
0@
1X
b1110 !
b1110 C
0&
0'
0(
1*
1+
1,
b10 #
b10 %
#590000
19
1q
1r
1H
0:
1m
1=
1V
1W
1@
1Y
1Z
1P
1>
1O
0B
1R
1A
1U
b10101 !
b10101 C
1&
1'
1(
b11 #
b11 %
#600000
0u
0G
0?
0]
0^
0d
0N
0r
08
1s
0t
0A
0Y
0e
0H
0g
1h
1;
1j
1k
0P
0O
0L
1:
0m
1K
19
0p
0q
1J
0V
0R
0U
0W
1@
0X
0Z
1>
0`
0=
1c
0<
0f
b11100 !
b11100 C
0&
0'
0(
0*
0+
0,
1.
1/
10
b100 #
b100 %
#610000
18
1t
1u
1G
09
1r
1H
0:
1m
1=
1d
1e
1L
0>
1`
1B
1A
b100011 !
b100011 C
1&
1'
1(
b101 #
b101 %
#620000
0r
1p
0H
1<
1f
1g
1:
0m
1?
1]
1^
0=
0c
0d
1N
0@
1X
b101010 !
b101010 C
0&
0'
0(
1*
1+
1,
b110 #
b110 %
#630000
19
1q
1r
1H
0:
1m
1=
1d
1e
1c
1V
1W
1L
1@
1Y
1Z
1P
0>
1`
1O
0B
1R
1A
1U
b110001 !
b110001 C
1&
1'
1(
b111 #
b111 %
#640000
0s
0;
0j
0k
08
0t
1u
0?
0]
0^
0J
1G
0N
0g
1r
0A
0Y
0K
1H
0P
0O
0d
0L
0:
1m
09
0p
0q
0V
0R
0U
0W
1@
0X
0Z
0>
0`
1=
0c
0e
0<
0f
0h
b0 !
b0 C
0&
0'
0(
0*
0+
0,
0.
0/
00
b0 "
b0 $
b0 #
b0 %
#650000
b1111 #
b1111 %
#660000
b1110 #
b1110 %
#670000
b1101 #
b1101 %
#680000
b1100 #
b1100 %
#690000
b1011 #
b1011 %
#700000
b1010 #
b1010 %
#710000
b1001 #
b1001 %
#720000
b1111 "
b1111 $
b0 #
b0 %
#730000
1D
1e
06
1{
1L
1j
0G
1E
1`
1J
09
0w
1A
1V
1W
1Z
0:
1]
0f
1M
0g
1h
0t
1I
0H
0F
1P
1O
1N
0?
0\
1K
0q
0;
0i
0m
0r
08
0u
0)
1R
1U
0@
0X
0-
0>
0=
0c
0<
01
02
03
04
07
1v
0x
b1 !
b1 C
1&
1'
1(
1*
1+
1,
1.
1/
10
15
b1111 #
b1111 %
#740000
0Z
0O
1e
0:
0W
1L
0=
0c
0d
0P
0>
1`
0@
1X
0Y
1B
0R
1A
0U
0V
1)
b10 !
b10 C
0&
0'
0(
b1110 #
b1110 %
#750000
09
0:
0]
0<
0f
0g
0=
0c
0d
0N
0?
1\
0^
0)
0@
0X
1-
b11 !
b11 C
1&
1'
1(
0*
0+
0,
b1101 #
b1101 %
#760000
0e
0:
0L
0=
1c
0d
1>
0`
1@
0B
0A
1)
b100 !
b100 C
0&
0'
0(
b1100 #
b1100 %
#770000
1D
06
1{
1E
07
1v
1I
1A
1V
1W
1Z
1]
1M
0j
08
1P
1O
1N
0?
0\
0:
0K
09
0J
0;
1i
0k
0)
1R
1U
0@
0X
0-
1>
0=
0c
0<
0h
11
b101 !
b101 C
1&
1'
1(
1*
1+
1,
0.
0/
00
b1011 #
b1011 %
#780000
0Z
0O
0:
0W
0=
0P
1>
0@
1X
0Y
1B
0R
1A
0U
0V
1)
b110 !
b110 C
0&
0'
0(
b1010 #
b1010 %
#790000
09
0:
0]
0<
0=
0N
0?
1\
0^
0)
0@
0X
1-
b111 !
b111 C
1&
1'
1(
0*
0+
0,
b1001 #
b1001 %
#800000
1w
1F
1u
1G
1r
1H
1D
1m
06
1{
1=
09
08
1E
0:
0>
1@
13
14
07
0v
12
0B
0A
1)
05
b0 !
b0 C
0&
0'
0(
b1110 "
b1110 $
b0 #
b0 %
#810000
1D
06
1{
0j
1G
1E
09
0J
0w
1Z
1]
0f
1M
1H
0g
0h
1t
0I
1F
1O
1N
0?
0\
0:
1m
0K
1q
1;
0i
0r
08
0u
1B
0)
1U
0@
0X
0-
1=
0c
1<
01
03
04
b10 !
b10 C
07
0v
1x
1'
1(
1+
1,
1/
10
15
b1111 #
b1111 %
#820000
1D
06
1{
1E
1x
1F
07
0v
0w
1t
0I
1G
1;
0j
1q
0J
1H
1<
0h
0:
1m
0K
0Z
1=
0c
1>
0O
0@
1X
0Y
b100 !
b100 C
0B
1A
0U
1)
0'
0(
b1110 #
b1110 %
#830000
1D
06
1{
1E
1x
1F
07
0v
0w
1t
0I
1G
1;
0j
1H
0h
09
1q
0J
0:
1m
0K
0]
1<
0f
1=
0c
0N
0?
1\
0^
b110 !
b110 C
1B
0)
0@
0X
1-
1'
1(
0+
0,
b1101 #
b1101 %
#840000
0x
0F
07
1v
0w
0t
1I
0G
0;
1j
0q
1J
0H
0<
1h
1:
0m
1K
0=
1c
0>
1@
b1000 !
b1000 C
0B
0A
1)
0'
0(
b1100 #
b1100 %
#850000
1D
06
1{
0w
0x
1E
0F
07
1v
0t
1I
0G
0q
1Z
1]
1M
0H
0j
08
1O
1N
0?
0\
1:
0m
0K
09
0J
0;
1i
0k
b1010 !
b1010 C
1B
0)
1U
0@
0X
0-
0=
0c
0<
0h
11
1'
1(
1+
1,
0/
00
b1011 #
b1011 %
#860000
09
0H
1:
0m
0Z
0=
1>
0O
0@
1X
0Y
b1100 !
b1100 C
0B
1A
0U
1)
0'
0(
b1010 #
b1010 %
#870000
0H
09
1:
0m
0]
0<
0=
0N
0?
1\
0^
b1110 !
b1110 C
1B
0)
0@
0X
1-
1'
1(
0+
0,
b1001 #
b1001 %
#880000
1w
1F
1u
1G
1r
1H
1D
0:
1m
06
1{
1=
08
1E
09
0>
1@
14
07
0v
13
b0 !
b0 C
0B
0A
1)
05
0'
0(
b1101 "
b1101 $
b0 #
b0 %
#890000
1D
1g
1h
06
1{
1K
0j
1G
1E
1d
1J
0r
0w
1L
0]
1f
0M
1t
0I
0H
1F
1`
0=
0N
1?
0\
09
1p
0q
1;
0i
0:
0m
08
0u
1A
0)
1B
1@
0X
0-
0>
1<
01
02
04
07
0v
1x
b11 !
b11 C
1&
1(
1*
1,
1.
10
15
b1111 #
b1111 %
#900000
1D
06
1{
1E
1x
1F
07
0v
0w
08
1t
0I
0J
1;
0j
0h
0f
0g
1M
0:
0K
0?
1]
0L
0=
0d
1N
1>
0`
0@
1X
0A
1)
b110 !
b110 C
0&
0(
b1110 #
b1110 %
#910000
1D
06
1{
1E
1x
1F
07
0v
0w
1t
0I
1G
1;
0j
09
1p
0J
1L
1:
0]
1<
0f
0>
1`
1=
0N
0?
1\
0^
1A
0)
0B
0@
0X
1-
b1001 !
b1001 C
1&
1(
0*
0,
b1101 #
b1101 %
#920000
1D
06
1{
1E
1x
1F
07
0v
0w
1t
0I
1G
1;
0j
09
1p
0J
1<
0h
1:
0K
0L
1=
0d
1>
0`
1@
0A
1)
b1100 !
b1100 C
0&
0(
b1100 #
b1100 %
#930000
1D
06
1{
1E
1x
1F
07
0v
0w
1:
0]
0M
1G
08
1t
0I
1=
0N
1?
0\
09
1p
1;
0i
1A
0)
1B
1@
0X
0-
1>
1<
11
b1111 !
b1111 C
1&
1(
1*
1,
0.
00
b1011 #
b1011 %
#940000
0x
0F
07
1v
0w
0G
08
0t
1I
19
0p
0;
1i
0<
1M
0:
0?
1]
0=
1N
0>
0@
1X
0A
1)
b10010 !
b10010 C
0&
0(
b1010 #
b1010 %
#950000
08
0G
19
0p
0:
0]
0<
1>
0=
0N
0?
1\
0^
1A
0)
0B
0@
0X
1-
b10101 !
b10101 C
1&
1(
0*
0,
b1001 #
b1001 %
#960000
1w
1F
1u
1G
09
1r
1H
1D
1m
06
1{
1=
08
1E
0:
0>
1@
14
07
0v
12
0A
1)
05
b0 !
b0 C
0&
0(
b1100 "
b1100 $
b0 #
b0 %
#970000
1D
06
1{
1r
0j
1E
1H
1J
0w
0:
1m
0]
1f
0M
1t
0I
1F
1>
1=
0N
1?
0\
09
0p
0q
1;
0i
08
0u
1A
0)
1@
0X
0-
0<
01
04
b100 !
b100 C
07
0v
1x
1(
1,
10
15
b1111 #
b1111 %
#980000
1D
06
1{
1E
1x
1F
07
0v
0w
08
1t
0I
0r
1p
0J
1;
0j
0H
1<
0f
1M
1:
0m
0?
1]
0=
1N
b1000 !
b1000 C
0>
0@
1X
0A
1)
0(
b1110 #
b1110 %
#990000
1D
06
1{
1E
1x
1F
07
0v
0w
1t
0I
0r
0q
1G
1;
0j
0H
09
1p
0J
1:
0m
0]
1<
0f
b1100 !
b1100 C
1>
0=
0N
0?
1\
0^
1A
0)
0@
0X
1-
1(
0,
b1101 #
b1101 %
#1000000
19
1q
1r
1H
0:
1m
1=
b10000 !
b10000 C
0>
1@
0A
1)
0(
b1100 #
b1100 %
#1010000
1D
06
1{
1E
1G
1r
1x
1H
1F
07
0v
0w
0:
1m
0]
0M
08
1t
0I
1>
1=
0N
1?
0\
b10100 !
b10100 C
19
1p
1q
1;
0i
1A
0)
1@
0X
0-
1<
11
1(
1,
00
b1011 #
b1011 %
#1020000
0x
0F
07
1v
0w
0G
08
0t
1I
0r
0p
0q
0;
1i
0H
0<
1M
1:
0m
0?
1]
0=
1N
b11000 !
b11000 C
0>
0@
1X
0A
1)
0(
b1010 #
b1010 %
#1030000
08
0r
0G
0H
19
0p
1:
0m
0]
0<
b11100 !
b11100 C
1>
0=
0N
0?
1\
0^
1A
0)
0@
0X
1-
1(
0,
b1001 #
b1001 %
#1040000
1w
1F
1u
1G
09
1r
1H
1D
0:
1m
06
1{
1=
1E
08
0>
1@
b0 !
b0 C
07
0v
14
0A
1)
05
0(
b1011 "
b1011 $
b0 #
b0 %
#1050000
1O
0e
1J
0w
0u
1W
0L
0M
1g
1s
0I
0H
0G
1@
1P
0`
1?
0\
1K
1;
0i
0m
09
0r
0)
1R
0A
0-
1>
0=
1c
01
02
03
07
0v
1x
b101 !
b101 C
1&
1'
1*
1+
1.
1/
15
b1111 #
b1111 %
#1060000
1D
06
1{
1E
1x
1F
07
0v
0w
08
1s
0I
1e
1d
1J
1;
0j
1L
1g
0M
0>
1`
0O
1:
1K
1?
0]
1A
0W
1=
1c
0N
0P
1@
0Y
1B
0R
1)
b1010 !
b1010 C
0&
0'
b1110 #
b1110 %
#1070000
1D
06
1{
1E
1x
1F
07
0v
0w
08
1s
0I
0K
0e
09
0J
1;
0j
0c
0d
0L
0<
0g
1M
0@
1>
0`
0?
1\
0)
0A
1-
b1111 !
b1111 C
1&
1'
0*
0+
b1101 #
b1101 %
#1080000
19
1<
0:
1K
0=
1c
1@
0B
1)
b10100 !
b10100 C
0&
0'
b1100 #
b1100 %
#1090000
1D
06
1{
1E
1x
1O
1F
07
0v
0w
1W
0M
08
1s
0I
1@
1P
1?
0\
1:
0K
1;
0i
0)
1R
0A
0-
0>
1=
0c
11
b11001 !
b11001 C
1&
1'
1*
1+
0.
0/
b1011 #
b1011 %
#1100000
1D
06
1{
1E
1x
1F
07
0v
0w
08
1s
0I
19
1;
0i
1<
0M
1>
0O
1:
1?
0]
1A
0W
1=
0N
0P
1@
0Y
1B
0R
1)
b11110 !
b11110 C
0&
0'
b1010 #
b1010 %
#1110000
0x
0F
07
1v
0w
18
0s
1I
0:
09
0;
1i
0=
0<
1M
0@
0>
0?
1\
0)
0A
1-
b100011 !
b100011 C
1&
1'
0*
0+
b1001 #
b1001 %
